rhubarbpy/__init__.py
rhubarbpy/_version.py
rhubarbpy/loopsum.py
rhubarbpy/subpkg/__init__.py
rhubarbpy/subpkg/hello.py
rhubarbpy-0.0.7.dist-info/METADATA
rhubarbpy-0.0.7.dist-info/WHEEL
rhubarbpy-0.0.7.dist-info/top_level.txt
rhubarbpy-0.0.7.dist-info/RECORD
